[
    {
        "gps": {
            "lat": 62.24829,
            "lng": 25.70975
        },
        "title": "First achivement unlocked 😀",
        "body": "Yes, Well done 🕺"
    },
    {
        "gps": {
            "lat": 62.24669,
            "lng": 25.71107
        },
        "title": "Second achivement unlocked 😀",
        "body": "Once again, Well done 🕺"
    },
    {
        "gps": {
            "lat": 62.22989,
            "lng": 25.74160
        },
        "title": "Welcome 😀",
        "body": "Welcome to JUY.🕺"
    }
]
